bin/__init__.py
bin/combine_delta_path_utils.py
combine_delta/__init__.py
combine_delta/delta.py
combine_delta/get_args.py
combine_delta/main.py
combine_delta/utils.py
combine_delta/version.py
combine_delta-0.0.2.data/scripts/combine_delta
combine_delta-0.0.2.dist-info/METADATA
combine_delta-0.0.2.dist-info/WHEEL
combine_delta-0.0.2.dist-info/entry_points.txt
combine_delta-0.0.2.dist-info/top_level.txt
combine_delta-0.0.2.dist-info/RECORD
